goodreads/__init__.py
goodreads/apikey.py
goodreads/author.py
goodreads/book.py
goodreads/client.py
goodreads/comment.py
goodreads/event.py
goodreads/ff-project.py
goodreads/group.py
goodreads/oath.py
goodreads/owned_book.py
goodreads/request.py
goodreads/review.py
goodreads/session.py
goodreads/shelf.py
goodreads/user.py
goodreads2-0.3.4.dist-info/DESCRIPTION.rst
goodreads2-0.3.4.dist-info/METADATA
goodreads2-0.3.4.dist-info/RECORD
goodreads2-0.3.4.dist-info/WHEEL
goodreads2-0.3.4.dist-info/metadata.json
goodreads2-0.3.4.dist-info/top_level.txt
