Metadata-Version: 2.0
Name: goodreads2
Version: 0.3.4
Summary: Python wrapper for Goodreads API
Home-page: https://github.com/tatianass/goodreads2
Author: Tatiana Saturno
Author-email: tatianassaturno@gmail.com
License: MIT
Keywords: goodreads API
Platform: UNKNOWN
Classifier: Development Status :: 4 - Beta
Classifier: Intended Audience :: Developers
Classifier: License :: OSI Approved :: MIT License
Classifier: Natural Language :: English
Classifier: Programming Language :: Python :: 2.7
Classifier: Programming Language :: Python :: 3.5
Requires-Dist: nose
Requires-Dist: rauth
Requires-Dist: requests
Requires-Dist: xmltodict
